Workbook
Name Aporte: APP!$D$17
Name patrimonio: APP!$D$20
Name qtd_anos: APP!$D$18
Name Rendimento_Carteira: APP!$D$13
Name salario: APP!$D$12
Name sugestao_investimento: APP!$D$14
Name taxa_mensal: APP!$D$19

Sheet APP
B11: CONFIGURAÇÕES
B12: Salário | D12: 4450
B13: Rendimento Carteira | D13: 0.006
B14: Sugestão de Investimento (30%) | D14: =salario*30% -> 1335
B16: INVESTIMENTO MENSAL
B17: Quanto investir por mês? | D17: 450
B18: Por quantos Anos? | D18: 10
B19: Taxa Rendimento mensal? | D19: 0.01079
B20: Patrimônio Acumulado? | D20: =FV(taxa_mensal,qtd_anos*12,Aporte*-1) -> 109477.9
B21: Divdendos Mensais? | D21: =patrimonio*Rendimento_Carteira -> 656.86737
B23: Cenários | D23: Dividendos
A24: 2 | B24: Quanto em 2 anos? | C24: =FV($D$19,$A24*12,$D$17*-1) -> 12252.432 | D24: =C24*Rendimento_Carteira -> 73.514594
A25: 5 | B25: Quanto em 5 anos? | C25: =FV($D$19,$A25*12,$D$17*-1) -> 37699.611 | D25: =C25*Rendimento_Carteira -> 226.19767
A26: 10 | B26: Quanto em 10 anos? | C26: =FV($D$19,$A26*12,$D$17*-1) -> 109477.9 | D26: =C26*Rendimento_Carteira -> 656.86737
A27: 20 | B27: Quanto em 20 anos? | C27: =FV($D$19,$A27*12,$D$17*-1) -> 506339.28 | D27: =C27*Rendimento_Carteira -> 3038.0357
A28: 30 | B28: Quanto em 30 anos? | C28: =FV($D$19,$A28*12,$D$17*-1) -> 1944976.3 | D28: =C28*Rendimento_Carteira -> 11669.858
B32: PERFIL | C32: Moderado
B33: VALOR A SER INVESTIDO POR MÊS | C33: =Aporte -> 450
B35: TIPO DE FII | C35: Percentual Sugerido | D35: Valores
B36: PAPEL | C36: =VLOOKUP($C$32&"-"&B36,Apoio!$B$3:$E$20,4,FALSE) -> 0.32 | D36: =C36*Aporte -> 144
B37: TIJOLO | C37: =VLOOKUP($C$32&"-"&B37,Apoio!$B$3:$E$20,4,FALSE) -> 0.35 | D37: =C37*Aporte -> 157.5
B38: HÍBRIDROS | C38: =VLOOKUP($C$32&"-"&B38,Apoio!$B$3:$E$20,4,FALSE) -> 0.08 | D38: =C38*Aporte -> 36
B39: FOFS | C39: =VLOOKUP($C$32&"-"&B39,Apoio!$B$3:$E$20,4,FALSE) -> 0.05 | D39: =C39*Aporte -> 22.5
B40: DESENVOLVIMENTO | C40: =VLOOKUP($C$32&"-"&B40,Apoio!$B$3:$E$20,4,FALSE) -> 0.1 | D40: =C40*Aporte -> 45
B41: HOTELARIAS | C41: =VLOOKUP($C$32&"-"&B41,Apoio!$B$3:$E$20,4,FALSE) -> 0.1 | D41: =C41*Aporte -> 45
D42: =SUM(D36:D41) -> 450

Sheet Apoio
B2: CHAVE | C2: PERFIL | D2: TIPOS DE FII | E2: %
B3: =C3&"-"&D3 -> Conservador-PAPEL | C3: Conservador | D3: PAPEL | E3: 0.3
B4: =C4&"-"&D4 -> Conservador-TIJOLO | C4: Conservador | D4: TIJOLO | E4: 0.5
B5: =C5&"-"&D5 -> Conservador-HÍBRIDROS | C5: Conservador | D5: HÍBRIDROS | E5: 0.1
B6: =C6&"-"&D6 -> Conservador-FOFS | C6: Conservador | D6: FOFS | E6: 0.1
B7: =C7&"-"&D7 -> Conservador-DESENVOLVIMENTO | C7: Conservador | D7: DESENVOLVIMENTO | E7: 0
B8: =C8&"-"&D8 -> Conservador-HOTELARIAS | C8: Conservador | D8: HOTELARIAS | E8: 0
B9: =C9&"-"&D9 -> Moderado-PAPEL | C9: Moderado | D9: PAPEL | E9: 0.32
B10: =C10&"-"&D10 -> Moderado-TIJOLO | C10: Moderado | D10: TIJOLO | E10: 0.35
B11: =C11&"-"&D11 -> Moderado-HÍBRIDROS | C11: Moderado | D11: HÍBRIDROS | E11: 0.08
B12: =C12&"-"&D12 -> Moderado-FOFS | C12: Moderado | D12: FOFS | E12: 0.05
B13: =C13&"-"&D13 -> Moderado-DESENVOLVIMENTO | C13: Moderado | D13: DESENVOLVIMENTO | E13: 0.1
B14: =C14&"-"&D14 -> Moderado-HOTELARIAS | C14: Moderado | D14: HOTELARIAS | E14: 0.1
... B20: =C20&"-"&D20 -> Agressivo-HOTELARIAS | C20: Agressivo | D20: HOTELARIAS | E20: 0.1
